running/__init__.py
running/__main__.py
running/__version__.py
running/benchmark.py
running/config.py
running/modifier.py
running/runtime.py
running/suite.py
running/util.py
running/command/__init__.py
running/command/fillin.py
running/command/genadvice.py
running/command/log_preprocessor.py
running/command/minheap.py
running/command/runbms.py
running/config/minheap_example.yml
running/config/runbms_example.yml
running/config/runbms_example_probes.yml
running/config/base/dacapo.yml
running/config/base/jvms.yml
running/config/base/minheap.yml
running/config/base/modifiers.yml
running/config/base/runbms-anu.yml
running/config/base/runbms.yml
running/config/base/specjbb2015.yml
running/config/base/specjvm98.yml
running/config/base/suites.yml
running/config/base/temurin.yml
running/plugin/__init__.py
running/plugin/runbms/__init__.py
running/plugin/runbms/copyfile.py
running/plugin/runbms/zulip.py
running_ng-0.4.7.dist-info/LICENSE
running_ng-0.4.7.dist-info/METADATA
running_ng-0.4.7.dist-info/WHEEL
running_ng-0.4.7.dist-info/entry_points.txt
running_ng-0.4.7.dist-info/top_level.txt
running_ng-0.4.7.dist-info/RECORD
