Metadata-Version: 2.1
Name: running-ng
Version: 0.4.7
Summary: Running: Next Generation
Author-email: Zixian Cai <u5937495@anu.edu.au>
License: Apache
Project-URL: Homepage, https://github.com/anupli/running-ng
Project-URL: Bug Tracker, https://github.com/anupli/running-ng/issues
Classifier: Development Status :: 3 - Alpha
Classifier: Intended Audience :: Science/Research
Classifier: License :: OSI Approved :: Apache Software License
Classifier: Topic :: System :: Benchmark
Classifier: Programming Language :: Python :: 3
Requires-Python: >=3.7
License-File: LICENSE
Requires-Dist: pyyaml ~=6.0.1
Provides-Extra: tests
Requires-Dist: pytest <8.4.0,>=7.4.4 ; extra == 'tests'
Requires-Dist: types-PyYAML ~=6.0.12 ; extra == 'tests'
Requires-Dist: mypy <1.12,>=1.8 ; extra == 'tests'
Provides-Extra: zulip
Requires-Dist: zulip ~=0.9.0 ; extra == 'zulip'
